tum_esm_lowcost_metadata/__init__.py
tum_esm_lowcost_metadata/interfaces.py
tum_esm_lowcost_metadata/py.typed
tum_esm_lowcost_metadata/types.py
tum_esm_lowcost_metadata-0.7.1.dist-info/METADATA
tum_esm_lowcost_metadata-0.7.1.dist-info/WHEEL
tum_esm_lowcost_metadata-0.7.1.dist-info/RECORD
