Metadata-Version: 2.1
Name: tum_esm_lowcost_metadata
Version: 0.7.1
Summary: Single source of truth for ESM's lowcost measurement logistics
Home-page: https://github.com/tum-esm/lowcost-metadata
Author: Moritz Makowski
Author-email: moritz.makowski@tum.de
Requires-Python: >=3.9,<4.0
Classifier: Programming Language :: Python :: 3
Classifier: Programming Language :: Python :: 3.9
Classifier: Programming Language :: Python :: 3.10
Classifier: Programming Language :: Python :: 3.11
Requires-Dist: deepdiff (>=6.3.0,<7.0.0)
Requires-Dist: pendulum (>=2.1.2,<3.0.0)
Requires-Dist: poetry-dotenv-plugin (>=0.2.0,<0.3.0)
Requires-Dist: poetry-plugin-dotenv (>=0.5.3,<0.6.0)
Requires-Dist: pydantic (>=1.10.4,<2.0.0)
Requires-Dist: tum-esm-utils (>=1.2.1,<2.0.0)
Project-URL: Repository, https://github.com/tum-esm/lowcost-metadata
